__init__.py
mutex.py
pywin_mutex-1.0.0.dist-info/LICENSE
pywin_mutex-1.0.0.dist-info/METADATA
pywin_mutex-1.0.0.dist-info/WHEEL
pywin_mutex-1.0.0.dist-info/top_level.txt
pywin_mutex-1.0.0.dist-info/RECORD
