Metadata-Version: 2.1
Name: pywin-mutex
Version: 1.0.0
Summary: A module for creating and using a shared mutex on Windows.
Author-email: Zvlbrg <MyGithubPage@github.com>
Project-URL: Homepage, https://github.com/Zvlbrg/pywin-mutex
Project-URL: Bug Tracker, https://github.com/Zvlbrg/pywin-mutex/issues
Classifier: Programming Language :: Python :: 3
Classifier: License :: OSI Approved :: MIT License
Classifier: Operating System :: Microsoft :: Windows
Requires-Python: >=3.9
License-File: LICENSE
Requires-Dist: pywin32
